quickMethods/__init__.py
quickMethods/main.py
quickmethods-0.0.1.dist-info/METADATA
quickmethods-0.0.1.dist-info/WHEEL
quickmethods-0.0.1.dist-info/top_level.txt
quickmethods-0.0.1.dist-info/RECORD
