Metadata-Version: 2.4
Name: quickMethods
Version: 0.0.1
Summary: A simple library to make your life faster with quick methods!
Author: Orly Neto
Author-email: orly2carvalhoneto@gmail.com
License: MIT License
Keywords: useful
Dynamic: author
Dynamic: author-email
Dynamic: description-content-type
Dynamic: keywords
Dynamic: license
Dynamic: summary
